steampy/__init__.py
steampy/chat.py
steampy/client.py
steampy/confirmation.py
steampy/exceptions.py
steampy/guard.py
steampy/login.py
steampy/market.py
steampy/models.py
steampy/utils.py
steampy_fixed-2.2.dist-info/LICENSE.txt
steampy_fixed-2.2.dist-info/METADATA
steampy_fixed-2.2.dist-info/WHEEL
steampy_fixed-2.2.dist-info/top_level.txt
steampy_fixed-2.2.dist-info/RECORD
