Metadata-Version: 2.1
Name: steampy-fixed
Version: 2.2
Summary: A Steam lib for trade automation(fixed)
Home-page: https://github.com/jiajiaxd/steampy-fixed
Author: jiajiaxd
Author-email: i@jiajiaxd.com
License: MIT
Download-URL: https://github.com/jiajiaxd/steampy-fixed/tarball/2.2
Keywords: steam,trade
Platform: UNKNOWN
License-File: LICENSE.txt
Requires-Dist: requests
Requires-Dist: beautifulsoup4
Requires-Dist: rsa
